7_FSM/2_MOORE_SEQUENCE_DETECTOR_1101/Moore1001.v
module SD1001(out,in,clk,reset);
    
    input in,clk,reset;
    output reg out;

    reg[2:0] state;
    parameter s0 = 0 , s1 = 1 , s2 = 2 , s3 = 3 ,s4 = 4;

    always @(posedge clk ) begin
        if(reset) 
            state<=s0;
        else begin
            case (state)
                s0:state=in?s1:s0;
                s1:state=in?s1:s2;
                s2:state=in?s1:s3;
                s3:state=in?s4:s0;
                s4:state=in?s1:s2; 
                default: state<=s0;
            endcase
        end
    end
    always @(state) begin
        case (state)
            s4:out<=1; 
            default: out<=0;
        endcase
    end

endmodule

7_FSM/2_MOORE_SEQUENCE_DETECTOR_1101/Moore1001_Tb.v
`timescale 1ns/1ps
`include "Moore1001.v"

module Moore_tb;

    reg in,reset,clk;
    wire out;

    SD1001 dut(out,in,clk,reset);

    initial begin
        // $monitor($time,"in=%b out=%b",in,out);
        $dumpfile("Moore1001.vcd");
        $dumpvars(0,Moore_tb);
    end

    always #5 clk=~clk;

    always @(posedge clk) begin
        $strobe($time,"   |  %b | %b ",in,out);
    end

    initial begin

        $display("                  ---------------");
        $display("                  Time | in | out");
        $display("                  ---------------");
        
        clk=0;
        reset=1;
        #7 reset=0;

        #2  in=1; 
        #10 in=0; #10 in=1; #10 in=0; #10 in=0;
        #10 in=1; #10 in=0; #10 in=0; #10 in=1;
        #10 in=1; #10 in=0; #10 in=0; #10 in=1;
        #10 $finish;
    end


endmodule

7_FSM/2_MOORE_SEQUENCE_DETECTOR_1101/Moore1001.vcd
$date
	Mon Jun 15 18:19:54 2026
$end
$version
	Icarus Verilog
$end
$timescale
	1ps
$end
$scope module Moore_tb $end
$var wire 1 ! out $end
$var reg 1 " clk $end
$var reg 1 # in $end
$var reg 1 $ reset $end
$scope module dut $end
$var wire 1 % clk $end
$var wire 1 & in $end
$var wire 1 ' reset $end
$var reg 1 ( out $end
$var reg 3 ) state [2:0] $end
$upscope $end
$upscope $end
$enddefinitions $end
#0
$dumpvars
bx )
x(
1'
x&
0%
1$
x#
0"
x!
$end
#5000
0(
0!
b0 )
1"
1%
#7000
0$
0'
#9000
1#
1&
#10000
0"
0%
#15000
b1 )
1"
1%
#19000
0#
0&
#20000
0"
0%
#25000
b10 )
1"
1%
#29000
1#
1&
#30000
0"
0%
#35000
b1 )
1"
1%
#39000
0#
0&
#40000
0"
0%
#45000
b10 )
1"
1%
#50000
0"
0%
#55000
b11 )
1"
1%
#59000
1#
1&
#60000
0"
0%
#65000
1(
1!
b100 )
1"
1%
#69000
0#
0&
#70000
0"
0%
#75000
0(
0!
b10 )
1"
1%
#80000
0"
0%
#85000
b11 )
1"
1%
#89000
1#
1&
#90000
0"
0%
#95000
1(
1!
b100 )
1"
1%
#100000
0"
0%
#105000
0(
0!
b1 )
1"
1%
#109000
0#
0&
#110000
0"
0%
#115000
b10 )
1"
1%
#120000
0"
0%
#125000
b11 )
1"
1%
#129000
1#
1&
#130000
0"
0%
#135000
1(
1!
b100 )
1"
1%
