5_SHIFT_REGISTER/BEHAVIOR_MODELING/1_SISO/SISO.v

module siso(Serail_out, Serial_in, clk, reset);

    input Serial_in,clk,reset;
    output Serail_out;

    reg [3:0] shift;
    
    assign Serail_out=shift[0];

    always @(posedge clk or posedge reset) begin
        if(reset) 
            shift<=4'b0000;
        else
            shift<={Serial_in,shift[3:1]};
        
    end

    
endmodule

5_SHIFT_REGISTER/BEHAVIOR_MODELING/1_SISO/SISO_TB.v

`include "SISO.v"

module siso_tb;

    reg clk, reset, Serial_in;
    wire Serail_out;

    siso dut(Serail_out,Serial_in,clk,reset);

    always #5 clk=~clk;

    initial begin
        $dumpfile("SISO.vcd");
        $dumpvars(0,siso_tb);
    end
    
    always @(posedge clk) begin
        $strobe($time,"  |   %b   |     %d     |     %d     ",reset,Serial_in,Serail_out);
    end

    initial begin

        $display("                ---------------------------------------");
        $display("                 Time | Reset | Serial_in | Serail_out ");
        $display("                ---------------------------------------");


        clk=0;
        reset=1;#7
        reset=0;

        Serial_in=1;#10
        Serial_in=0;#10
        Serial_in=1;#10
        Serial_in=1;#10
        Serial_in=0;#10
        $finish;
    end

endmodule

5_SHIFT_REGISTER/BEHAVIOR_MODELING/1_SISO/SISO.vcd
$date
	Mon Jun 15 13:39:47 2026
$end
$version
	Icarus Verilog
$end
$timescale
	1s
$end
$scope module siso_tb $end
$var wire 1 ! Serail_out $end
$var reg 1 " Serial_in $end
$var reg 1 # clk $end
$var reg 1 $ reset $end
$scope module dut $end
$var wire 1 ! Serail_out $end
$var wire 1 % Serial_in $end
$var wire 1 & clk $end
$var wire 1 ' reset $end
$var reg 4 ( shift [3:0] $end
$upscope $end
$upscope $end
$enddefinitions $end
#0
$dumpvars
b0 (
1'
0&
x%
1$
0#
x"
0!
$end
#5
1#
1&
#7
1"
1%
0$
0'
#10
0#
0&
#15
b1000 (
1#
1&
#17
0"
0%
#20
0#
0&
#25
b100 (
1#
1&
#27
1"
1%
#30
0#
0&
#35
b1010 (
1#
1&
#40
0#
0&
#45
1!
b1101 (
1#
1&
#47
0"
0%
#50
0#
0&
#55
0!
b110 (
1#
1&
