2_COMBINATIONAL_CIRCUITS/Structural_Modeling/5_MULTIPLEXER/MUX_2X1/Mux_2X1.v
module Mux_2X1(Y,I0,I1,S);

    input I0, I1, S;
    output Y;
    wire w0,w1,w2;

    not n(w0,S);

    and M0(w1,I0,w0);
    and M1(w2,I1,S);
    or Mu(Y,w1,w2);

endmodule

2_COMBINATIONAL_CIRCUITS/Structural_Modeling/5_MULTIPLEXER/MUX_8X1/Mux_4X1.v
module Mux_4X1(Y, I0, I1, I2, I3, S1, S0);

    input I0, I1, I2, I3, S0, S1;
    output Y;

    wire S0_n, S1_n;
    wire w0, w1, w2, w3;

    not n(S0_n,S0); 
    not n1(S1_n,S1); 

    and m0(w0,I0,S1_n,S0_n);
    and m1(w1,I1,S1_n,S0);
    and m2(w2,I2,S1,S0_n);
    and m3(w3,I3,S1,S0);

    or mux(Y,w0,w1,w2,w3);

endmodule

2_COMBINATIONAL_CIRCUITS/Structural_Modeling/5_MULTIPLEXER/MUX_8X1/Mux_8X1.v
//Designing Structural modeled 8X1 Multiplexer using 2 Structural modeled 4X1 Multiplexer and 1 2X1 Multiplexer

`include "Mux_4X1.v"
`include "Mux_2X1.v"

module Mux_8X1(Y, I, S);

    input [0:7] I;
    input [2:0] S;
    output Y;

    wire M0, M1;

    Mux_4X1 Mux0(M0,I[0],I[1],I[2],I[3],S[1],S[0]);
    Mux_4X1 Mux1(M1,I[4],I[5],I[6],I[7],S[1],S[0]);
    Mux_2X1 Mux2(Y,M0,M1,S[2]);

endmodule

2_COMBINATIONAL_CIRCUITS/Structural_Modeling/5_MULTIPLEXER/MUX_8X1/Mux_8X1_Tb.v
`include "Mux_8X1.v"

module Mux_8X1_Tb;

    reg [7:0] I;
    reg [2:0] S;
    wire Y;

    Mux_8X1 dut(Y,I,S);

    initial begin
        $dumpfile("Mux_8X1.vcd");
        $dumpvars(0,Mux_8X1_Tb);
    end

    initial begin
        $monitor($time," I=%b  S=%b  Y=%b", I, S, Y);

        I=8'b10011010;
        S=0;
        #10 S=1;
        #10 S=2;
        #10 S=3;
        #10 S=4;
        #10 S=5;
        #10 S=6;
        #10 S=7;
        #10 $finish;

    end


endmodule

2_COMBINATIONAL_CIRCUITS/Structural_Modeling/5_MULTIPLEXER/MUX_8X1/Mux_8X1.vcd
$date
	Mon Apr 13 19:16:03 2026
$end
$version
	Icarus Verilog
$end
$timescale
	1s
$end
$scope module Mux_8X1_Tb $end
$var wire 1 ! Y $end
$var reg 8 " I [7:0] $end
$var reg 3 # S [2:0] $end
$scope module dut $end
$var wire 8 $ I [0:7] $end
$var wire 1 % M0 $end
$var wire 1 & M1 $end
$var wire 3 ' S [2:0] $end
$var wire 1 ! Y $end
$scope module Mux0 $end
$var wire 1 ( I0 $end
$var wire 1 ) I1 $end
$var wire 1 * I2 $end
$var wire 1 + I3 $end
$var wire 1 , S0 $end
$var wire 1 - S0_n $end
$var wire 1 . S1 $end
$var wire 1 / S1_n $end
$var wire 1 % Y $end
$var wire 1 0 w0 $end
$var wire 1 1 w1 $end
$var wire 1 2 w2 $end
$var wire 1 3 w3 $end
$upscope $end
$scope module Mux1 $end
$var wire 1 4 I0 $end
$var wire 1 5 I1 $end
$var wire 1 6 I2 $end
$var wire 1 7 I3 $end
$var wire 1 8 S0 $end
$var wire 1 9 S0_n $end
$var wire 1 : S1 $end
$var wire 1 ; S1_n $end
$var wire 1 & Y $end
$var wire 1 < w0 $end
$var wire 1 = w1 $end
$var wire 1 > w2 $end
$var wire 1 ? w3 $end
$upscope $end
$scope module Mux2 $end
$var wire 1 % I0 $end
$var wire 1 & I1 $end
$var wire 1 @ S $end
$var wire 1 ! Y $end
$var wire 1 A w0 $end
$var wire 1 B w1 $end
$var wire 1 C w2 $end
$upscope $end
$upscope $end
$upscope $end
$enddefinitions $end
#0
$dumpvars
0C
1B
1A
0@
0?
0>
0=
1<
1;
0:
19
08
07
16
05
14
03
02
01
10
1/
0.
1-
0,
1+
0*
0)
1(
b0 '
1&
1%
b10011010 $
b0 #
b10011010 "
1!
$end
#10
0!
0B
0%
0&
00
0<
0-
09
1,
18
b1 #
b1 '
#20
1&
0/
1-
0;
1>
19
1.
0,
1:
08
b10 #
b10 '
#30
1!
1B
0&
1%
0>
0-
13
09
1,
18
b11 #
b11 '
#40
1C
1&
1!
10
1%
1<
0B
1/
1-
03
1;
19
0A
0.
0,
0:
08
1@
b100 #
b100 '
#50
0!
0C
0%
0&
00
0<
0-
09
1,
18
b101 #
b101 '
#60
1!
1C
1&
0/
1-
0;
1>
19
1.
0,
1:
08
b110 #
b110 '
#70
0!
0C
0&
1%
0>
0-
13
09
1,
18
b111 #
b111 '
