5_SHIFT_REGISTER/BEHAVIOR_MODELING/4_PIPO/PIPO.v

module pipo(parallel_out,parallel_in,clk,reset);

    input [3:0] parallel_in;
    input clk,reset;
    output reg [3:0] parallel_out;

    always @(posedge clk or posedge reset) begin
        if(reset)
            parallel_out<=4'b0000;
        else
            parallel_out<=parallel_in;
    end

endmodule

5_SHIFT_REGISTER/BEHAVIOR_MODELING/4_PIPO/PIPO_TB.v

`include "PIPO.v"

module pipo_tb;

    reg [3:0] parallel_in;
    reg clk,reset;
    wire [3:0] parallel_out;

    pipo dut(parallel_out, parallel_in, clk, reset);

    always #5 clk=~clk;

    initial begin
        $dumpfile("PIPO.vcd");
        $dumpvars(0,pipo_tb);
    end

    always @(posedge clk) begin
        $strobe($time,"  |   %b   |      %d     |     %d     ",reset,parallel_in,parallel_out);
    end

    initial begin
        $display("                -------------------------------------------");
        $display("                 Time | Reset | parallel_in | parallel_out ");
        $display("                -------------------------------------------");

        clk=0;
        reset=1;
        parallel_in=4'b1001;#10
        reset=0;

        parallel_in=4'b1011;#10
        parallel_in=4'b1000;#10
        parallel_in=4'b1001;#10
        parallel_in=4'b0110;#10
        $finish;

    end

endmodule

5_SHIFT_REGISTER/BEHAVIOR_MODELING/4_PIPO/PIPO.vcd
$date
	Mon Jun 15 13:47:21 2026
$end
$version
	Icarus Verilog
$end
$timescale
	1s
$end
$scope module pipo_tb $end
$var wire 4 ! parallel_out [3:0] $end
$var reg 1 " clk $end
$var reg 4 # parallel_in [3:0] $end
$var reg 1 $ reset $end
$scope module dut $end
$var wire 1 % clk $end
$var wire 4 & parallel_in [3:0] $end
$var wire 1 ' reset $end
$var reg 4 ( parallel_out [3:0] $end
$upscope $end
$upscope $end
$enddefinitions $end
#0
$dumpvars
b0 (
1'
b1001 &
0%
1$
b1001 #
0"
b0 !
$end
#5
1"
1%
#10
0"
0%
b1011 #
b1011 &
0$
0'
#15
b1011 (
b1011 !
1"
1%
#20
0"
0%
b1000 #
b1000 &
#25
b1000 (
b1000 !
1"
1%
#30
0"
0%
b1001 #
b1001 &
#35
b1001 (
b1001 !
1"
1%
#40
0"
0%
b110 #
b110 &
#45
b110 (
b110 !
1"
1%
