5_SHIFT_REGISTER/STRUCTURAL_MODELING/1_SISO/D_FF.v


module d_ff(Q,D,clk,reset);

    input D,clk,reset;
    output reg Q;

    always @(posedge clk ) begin
        if(reset)
            Q<=0;
        else
            Q<=D;
    end

endmodule

5_SHIFT_REGISTER/STRUCTURAL_MODELING/1_SISO/SISO.v


`include "D_FF.v"

module siso(Serial_out, Serial_in, clk,reset);

    input Serial_in,clk,reset;
    output Serial_out;

    wire w1,w2,w3;

    d_ff d0(w1,Serial_in,clk,reset);
    d_ff d1(w2,w1,clk,reset);
    d_ff d2(w3,w2,clk,reset);
    d_ff d3(Serial_out,w3,clk,reset);
    
    
endmodule

5_SHIFT_REGISTER/STRUCTURAL_MODELING/1_SISO/SISO_TB.v

`include "SISO.v"

module siso_tb;

    reg clk, Serial_in,reset;
    wire Serail_out;

    siso dut(Serail_out,Serial_in,clk,reset);

    always #5 clk=~clk;

    initial begin
        $dumpfile("SISO.vcd");
        $dumpvars(0,siso_tb);
    end

    always @(posedge clk) begin
        $strobe($time,"  |   %b   |     %d     |     %d     ",reset,Serial_in,Serail_out);
    end

    initial begin
        $display("                ---------------------------------------");
        $display("                 Time | Reset | Serial_in | Serail_out ");
        $display("                ---------------------------------------");

        clk=0;
        reset=1;#7
        reset=0;

        Serial_in=0;#10
        Serial_in=1;#10
        Serial_in=0;#10
        Serial_in=1;#10
        Serial_in=1;#10
        Serial_in=0;#10
        $finish;
    end

endmodule

5_SHIFT_REGISTER/STRUCTURAL_MODELING/1_SISO/SISO.vcd
$date
	Mon Jun 15 16:32:11 2026
$end
$version
	Icarus Verilog
$end
$timescale
	1s
$end
$scope module siso_tb $end
$var wire 1 ! Serail_out $end
$var reg 1 " Serial_in $end
$var reg 1 # clk $end
$var reg 1 $ reset $end
$scope module dut $end
$var wire 1 % Serial_in $end
$var wire 1 ! Serial_out $end
$var wire 1 & clk $end
$var wire 1 ' reset $end
$var wire 1 ( w1 $end
$var wire 1 ) w2 $end
$var wire 1 * w3 $end
$scope module d0 $end
$var wire 1 % D $end
$var wire 1 & clk $end
$var wire 1 ' reset $end
$var reg 1 + Q $end
$upscope $end
$scope module d1 $end
$var wire 1 ( D $end
$var wire 1 & clk $end
$var wire 1 ' reset $end
$var reg 1 , Q $end
$upscope $end
$scope module d2 $end
$var wire 1 ) D $end
$var wire 1 & clk $end
$var wire 1 ' reset $end
$var reg 1 - Q $end
$upscope $end
$scope module d3 $end
$var wire 1 * D $end
$var wire 1 & clk $end
$var wire 1 ' reset $end
$var reg 1 . Q $end
$upscope $end
$upscope $end
$upscope $end
$enddefinitions $end
#0
$dumpvars
x.
x-
x,
x+
x*
x)
x(
1'
0&
x%
1$
0#
x"
x!
$end
#5
0+
0(
0,
0)
0-
0*
0.
0!
1#
1&
#7
0"
0%
0$
0'
#10
0#
0&
#15
1#
1&
#17
1"
1%
#20
0#
0&
#25
1+
1(
1#
1&
#27
0"
0%
#30
0#
0&
#35
1,
1)
0+
0(
1#
1&
#37
1"
1%
#40
0#
0&
#45
1+
1(
0,
0)
1-
1*
1#
1&
#50
0#
0&
#55
1.
1!
0-
0*
1,
1)
1#
1&
#57
0"
0%
#60
0#
0&
#65
0+
0(
1-
1*
0.
0!
1#
1&
