2_COMBINATIONAL_CIRCUITS/Behavioral_Modeling/1_HALF_ADDER/Half_Adder.v
module Half_Adder(sum, carry, A, B);

    input A, B;
    output reg sum, carry;

    always @(*) begin
        {carry,sum}=A+B;
    end

endmodule

2_COMBINATIONAL_CIRCUITS/Dataflow_Modeling/1_HALF_ADDER/Half_Adder_Tb.v
`timescale 1ns/1ps
`include "Half_Adder.v"

module Half_Adder_Tb;
    
  reg A, B;
  wire sum, carry;

  integer i,j;
  reg [3:0] val;

  Half_Adder DUT (sum, carry, A, B);

  initial begin
    $dumpfile("Half_Adder.vcd");
    $dumpvars(0,Half_Adder_Tb);
  end

  initial begin
    val[0]=1'b0;
    val[1]=1'b1;
    val[2]=1'bx;
    val[3]=1'bz;

    $display("\t\t\t\t ","---------------------------");
    $display("\t\t\t\t  ","time| A | B | sum | carry");
    $display("\t\t\t\t ","---------------------------");

    for(i=0;i<2;i=i+1)begin
      A=val[i];
      for(j=0;j<2;j=j+1)begin
        B=val[j];
        #5 $write($time,"  | %b | %b |  %b  |  %b\n",A,B,sum,carry);
      end
    end

    $display("\t\t\t\t ","-------------------------");

    for(i=2;i<4;i=i+1)begin
      A=val[i];
      for(j=0;j<4;j=j+1)begin
        B=val[j];
        #5 $write($time,"  | %b | %b |  %b  |  %b\n",A,B,sum,carry);
      end
    end
    
    #5 $finish;

  end

endmodule

2_COMBINATIONAL_CIRCUITS/Behavioral_Modeling/1_HALF_ADDER/Half_Adder.vcd
$date
	Thu Apr 09 22:59:39 2026
$end
$version
	Icarus Verilog
$end
$timescale
	1ps
$end
$scope module Half_Adder_Tb $end
$var wire 1 ! carry $end
$var wire 1 " sum $end
$var reg 1 # A $end
$var reg 1 $ B $end
$var integer 32 % i [31:0] $end
$var integer 32 & j [31:0] $end
$var reg 4 ' val [3:0] $end
$scope module DUT $end
$var wire 1 ( A $end
$var wire 1 ) B $end
$var reg 1 * carry $end
$var reg 1 + sum $end
$upscope $end
$upscope $end
$enddefinitions $end
#0
$dumpvars
0+
0*
0)
0(
bzx10 '
b0 &
b0 %
0$
0#
0"
0!
$end
#5000
1+
1"
1$
1)
b1 &
#10000
0$
0)
1#
1(
b1 %
b0 &
#15000
1*
1!
0+
0"
1$
1)
b1 &
#20000
x*
x!
x+
x"
0$
0)
x#
x(
b10 %
b0 &
#25000
1$
1)
b1 &
#30000
x$
x)
b10 &
#35000
z$
z)
b11 &
#40000
0$
0)
z#
z(
b11 %
b0 &
#45000
1$
1)
b1 &
#50000
x$
x)
b10 &
#55000
z$
z)
b11 &
#60000
b100 %
b100 &
