3_SEQUENTIAL_CIRCUITS/Behavioral_Modeling/LATCH/SR_LATCH/Sr_Latch.v
module Sr_Latch(Q, Q_bar, S, R, En);

input S, R, En;
output reg Q;
output Q_bar;

assign Q_bar = ~Q;

always @(S or R or En)
begin
    if (En) begin
        if (S==1 && R==1)
            Q <= 1'bx;
        else if (S)
            Q <= 1;
        else if (R)
            Q <= 0;
    end
end

endmodule

3_SEQUENTIAL_CIRCUITS/Behavioral_Modeling/LATCH/SR_LATCH/Sr_Latch_Tb.v
`include "Sr_Latch.v"

module Sr_Latch_Tb;

    reg S, R, En;
    wire Q, Q_bar;

    Sr_Latch dut(Q,Q_bar,S,R,En);

    initial begin
        $dumpfile("Sr_Latch.vcd");
        $dumpvars(0,Sr_Latch_Tb);
    end

    initial begin
        $display("----------------------");
        $display(" EN | S | R || Q | Q_bar ");
        $display("----------------------");
        $monitor("  %b | %b | %b || %b | %b ",En,S,R,Q,Q_bar);

        En=0;
        S=0;R=0;#10
        En=1;
        S=0;R=0;#10
        S=0;R=1;#10
        S=0;R=0;#10 
        S=1;R=0;#10
        S=0;R=0;#10
        S=1;R=1;#10;
        S=1;R=0;#10
        En=0;
        S=0;R=0;#10
        $finish;


    end

endmodule

3_SEQUENTIAL_CIRCUITS/Behavioral_Modeling/LATCH/SR_LATCH/Sr_Latch.vcd
$date
	Mon Jun 15 11:26:44 2026
$end
$version
	Icarus Verilog
$end
$timescale
	1s
$end
$scope module Sr_Latch_Tb $end
$var wire 1 ! Q $end
$var wire 1 " Q_bar $end
$var reg 1 # En $end
$var reg 1 $ R $end
$var reg 1 % S $end
$scope module dut $end
$var wire 1 & En $end
$var wire 1 " Q_bar $end
$var wire 1 ' R $end
$var wire 1 ( S $end
$var reg 1 ) Q $end
$upscope $end
$upscope $end
$enddefinitions $end
#0
$dumpvars
x)
0(
0'
0&
0%
0$
0#
x"
x!
$end
#10
1#
1&
#20
1"
0)
0!
1$
1'
#30
0$
0'
#40
0"
1)
1!
1%
1(
#50
0%
0(
#60
1)
1!
1$
1'
1%
1(
#70
0$
0'
#80
0%
0(
0#
0&
