2_COMBINATIONAL_CIRCUITS/Structural_Modeling/5_MULTIPLEXER/MUX_2X1/Mux_2X1.v
module Mux_2X1(Y,I0,I1,S);

    input I0, I1, S;
    output Y;
    wire w0,w1,w2;

    not n(w0,S);

    and M0(w1,I0,w0);
    and M1(w2,I1,S);
    or Mu(Y,w1,w2);

endmodule

2_COMBINATIONAL_CIRCUITS/Dataflow_Modeling/5_MULTIPLEXER/MUX_2X1/Mux_2X1_Tb.v
`timescale 1ns/1ps
`include "Mux_2X1.v"

module Mux_2X1_Tb;

reg I0, I1, S;
wire Y;

Mux_2X1 uut (Y,I0,I1,S);

initial begin
    $dumpfile("Mux_2X1.vcd");
    $dumpvars(0,Mux_2X1_Tb);
end

initial
begin
    $display("-------------");
    $display("I0| I1| S | Y");
    $display("-------------");
    $monitor("%b | %b | %b | %b", I0, I1, S, Y);

    I0 = 0; I1 = 0; S = 0; 
    #10 I0 = 0; I1 = 1; S = 0; 
    #10 I0 = 1; I1 = 0; S = 0; 
    #10 I0 = 1; I1 = 1; S = 0; 
    #10 I0 = 0; I1 = 0; S = 1; 
    #10 I0 = 0; I1 = 1; S = 1; 
    #10 I0 = 1; I1 = 0; S = 1; 
    #10 I0 = 1; I1 = 1; S = 1;
    #10 $display("-------------");
        I0 = 1'bx; I1 = 1'bz; S = 1;
    #10 I0 = 1'bx; I1 = 1'bz; S = 0;
    #10 I0 = 1; I1 = 0; S = 1'bz;
    #10 I0 = 1; I1 = 0; S = 1'bx;
    #10 $display("-------------");
        $finish;

end

endmodule

2_COMBINATIONAL_CIRCUITS/Structural_Modeling/5_MULTIPLEXER/MUX_2X1/Mux_2X1.vcd
$date
	Thu Apr 09 23:10:21 2026
$end
$version
	Icarus Verilog
$end
$timescale
	1ps
$end
$scope module Mux_2X1_Tb $end
$var wire 1 ! Y $end
$var reg 1 " I0 $end
$var reg 1 # I1 $end
$var reg 1 $ S $end
$scope module uut $end
$var wire 1 % I0 $end
$var wire 1 & I1 $end
$var wire 1 ' S $end
$var wire 1 ! Y $end
$var wire 1 ( w0 $end
$var wire 1 ) w1 $end
$var wire 1 * w2 $end
$upscope $end
$upscope $end
$enddefinitions $end
#0
$dumpvars
0*
0)
1(
0'
0&
0%
0$
0#
0"
0!
$end
#10000
1#
1&
#20000
1!
1)
0#
0&
1"
1%
#30000
1#
1&
#40000
0!
0(
0)
1$
1'
0#
0&
0"
0%
#50000
1!
1*
1#
1&
#60000
0!
0*
0#
0&
1"
1%
#70000
1!
1*
1#
1&
#80000
x!
x*
z#
z&
x"
x%
#90000
x)
x!
1(
0*
0$
0'
#100000
x!
x(
x)
z$
z'
0#
0&
1"
1%
#110000
x$
x'
