4_REGISTERS/4_BIT_REGISTER_BHEVIORAL/4_Bit_Reg.v
//Simple 4 Bit Register Register with Asynchronous Reset and Enable 
// Behavioral Modeling
// This is a common and practical implementation that uses an asynchronous reset and a synchronous enable signal. 

module fourbit_reg(D,Q,clk,reset);

    input [3:0] Q;
    input clk,reset;
    output reg [3:0] D;

    always @(posedge clk or posedge reset) begin
        if(reset)begin
            D<=4'b0000;
        end
        else begin
            D<=Q;
        end
    end

endmodule

4_REGISTERS/4_BIT_REGISTER_BHEVIORAL/4_Bit_Reg_Tb.v


`include "4_Bit_Reg.v"

module fourbit_reg_tb;

    reg [3:0] Q ;
    reg clk, reset;
    wire [3:0] D ;

    fourbit_reg dut(D,Q,clk,reset);

    always #5 clk = ~clk;

    initial begin
        $dumpfile("4_Bit_Reg.vcd");
        $dumpvars(0,fourbit_reg_tb);
    end

    always @(posedge clk) begin
        $strobe($time,"  |   %b   | %d | %d ",reset,Q,D);
    end

    initial begin

        $display("                -----------------------");
        $display("                 Time | Reset | Q  | D ");
        $display("                -----------------------");


        clk=0;
        #7
        Q=4'b0010;#10
        Q=4'b0101;#10
        Q=4'b1111;#10
        Q=4'b1011;#10
        $finish;
    end

    initial begin
        reset=1;#7
        reset=0;
    end

endmodule

4_REGISTERS/4_BIT_REGISTER_BHEVIORAL/4_Bit_Reg.vcd
$date
	Mon Jun 15 13:27:33 2026
$end
$version
	Icarus Verilog
$end
$timescale
	1s
$end
$scope module fourbit_reg_tb $end
$var wire 4 ! D [3:0] $end
$var reg 4 " Q [3:0] $end
$var reg 1 # clk $end
$var reg 1 $ reset $end
$scope module dut $end
$var wire 4 % Q [3:0] $end
$var wire 1 & clk $end
$var wire 1 ' reset $end
$var reg 4 ( D [3:0] $end
$upscope $end
$upscope $end
$enddefinitions $end
#0
$dumpvars
b0 (
1'
0&
bx %
1$
0#
bx "
b0 !
$end
#5
1#
1&
#7
0$
0'
b10 "
b10 %
#10
0#
0&
#15
b10 (
b10 !
1#
1&
#17
b101 "
b101 %
#20
0#
0&
#25
b101 (
b101 !
1#
1&
#27
b1111 "
b1111 %
#30
0#
0&
#35
b1111 (
b1111 !
1#
1&
#37
b1011 "
b1011 %
#40
0#
0&
#45
b1011 (
b1011 !
1#
1&
