2_COMBINATIONAL_CIRCUITS/Dataflow_Modeling/5_MULTIPLEXER/Mux_4X1/Mux_4X1.v
module Mux_4X1(Y,I0,I1,I2,I3,S0,S1);

    input I0,I1,I2,I3,S0,S1;
    output Y;

    assign Y= (I0 & ~S1 & ~S0) | (I1 & ~S1 & S0) | (I2 & S1 & ~S0) | (I3 & S1 & S0);

endmodule

2_COMBINATIONAL_CIRCUITS/Structural_Modeling/5_MULTIPLEXER/MUX_4X1/Mux_4X1_Tb.v
`include "Mux_4X1.v"

module Mux_4X1_Tb;

    reg I0, I1, I2, I3, S1, S0;
    wire Y;

    Mux_4X1 dut(Y,I0,I1,I2,I3,S0,S1);

    initial begin
        $dumpfile("Mux_4X1.vcd");
        $dumpvars(0,Mux_4X1_Tb);
    end

    initial begin
        
        $display("-------------------");
        $display("   I  | S1 | S0 | Y");
        $display("-------------------");
        $monitor(" %b%b%b%b | %b  | %b  | %b",I0,I1,I2,I3,S1,S0,Y);

        I0=0; I1=1; I2=0; I3=1;
        S1=0; S0=0; #10;   
        S1=0; S0=1; #10;   
        S1=1; S0=0; #10;   
        S1=1; S0=1; #10; 
        $display("-------------------");
        S1=1; S0=1;I2=1'bx; #10; 
        S1=1; S0=1;I3=1'bx; #10; 
        S1=1'bx; S0=1; #10; 
        S1=1'bx; S0=1'bz; #10; 
        S1=1'b1; S0=1'bz; #10; 

        #10 $display("-------------------");
            $finish;
    end

endmodule

2_COMBINATIONAL_CIRCUITS/Dataflow_Modeling/5_MULTIPLEXER/Mux_4X1/Mux_4X1.vcd
$date
	Thu Apr 09 23:09:41 2026
$end
$version
	Icarus Verilog
$end
$timescale
	1s
$end
$scope module Mux_4X1_Tb $end
$var wire 1 ! Y $end
$var reg 1 " I0 $end
$var reg 1 # I1 $end
$var reg 1 $ I2 $end
$var reg 1 % I3 $end
$var reg 1 & S0 $end
$var reg 1 ' S1 $end
$scope module dut $end
$var wire 1 ( I0 $end
$var wire 1 ) I1 $end
$var wire 1 * I2 $end
$var wire 1 + I3 $end
$var wire 1 , S0 $end
$var wire 1 - S1 $end
$var wire 1 ! Y $end
$upscope $end
$upscope $end
$enddefinitions $end
#0
$dumpvars
0-
0,
1+
0*
1)
0(
0'
0&
1%
0$
1#
0"
0!
$end
#10
1!
1&
1,
#20
0!
0&
0,
1'
1-
#30
1!
1&
1,
#40
x$
x*
#50
x!
x%
x+
#60
x'
x-
#70
z&
z,
#80
1'
1-
