3_SEQUENTIAL_CIRCUITS/Behavioral_Modeling/FLIP_FLOP/T_FF/T_FF.v
//Asychnorous

module T_FF(Q, Q_bar, T, clk, reset);

    input T, clk,reset;
    output reg Q;
    output Q_bar;


    always @(posedge clk or posedge reset ) begin
        if (reset==1)begin
            Q<=0;
        end
        else begin
            if(T)
                Q<=~Q;
            else
                Q<=Q;
        end
    end

    assign Q_bar = ~Q; 

endmodule

3_SEQUENTIAL_CIRCUITS/Behavioral_Modeling/FLIP_FLOP/T_FF/T_FF_Tb.v
`include "T_FF.v"
`timescale 1ns/1ps

module T_FF_Tb;

reg T, clk, reset;
wire Q, Q_bar;

always #5 clk = ~clk;

T_FF dut(Q, Q_bar, T, clk, reset);

initial
begin
    $dumpfile("T_FF.vcd");
    $dumpvars(0, T_FF_Tb);
end

always @(posedge clk) begin
    $strobe($time,"  |  %b   | %b || %b |  %b ",reset,T,Q,Q_bar);
end

initial
begin
    $display("                 -----------------------------");
    $display("                 Time |Reset | T || Q | Q_bar ");
    $display("                 -----------------------------");

    clk = 0;
    #2
    #2  T=0; 
    reset=1;
    #10 T=1; 
    reset=0; 
    #10 T=1;  
    #10 T=0; 
    #10 T=1;  
    #10 T=0;

    #20 $finish;
end

endmodule

3_SEQUENTIAL_CIRCUITS/Behavioral_Modeling/FLIP_FLOP/T_FF/T_FF.vcd
$date
	Mon Jun 15 12:11:02 2026
$end
$version
	Icarus Verilog
$end
$timescale
	1ps
$end
$scope module T_FF_Tb $end
$var wire 1 ! Q $end
$var wire 1 " Q_bar $end
$var reg 1 # T $end
$var reg 1 $ clk $end
$var reg 1 % reset $end
$scope module dut $end
$var wire 1 " Q_bar $end
$var wire 1 & T $end
$var wire 1 ' clk $end
$var wire 1 ( reset $end
$var reg 1 ) Q $end
$upscope $end
$upscope $end
$enddefinitions $end
#0
$dumpvars
x)
x(
0'
x&
x%
0$
x#
x"
x!
$end
#4000
1"
0)
0!
1%
1(
0#
0&
#5000
1$
1'
#10000
0$
0'
#14000
0%
0(
1#
1&
#15000
0"
1)
1!
1$
1'
#20000
0$
0'
#25000
1"
0)
0!
1$
1'
#30000
0$
0'
#34000
0#
0&
#35000
1$
1'
#40000
0$
0'
#44000
1#
1&
#45000
0"
1)
1!
1$
1'
#50000
0$
0'
#54000
0#
0&
