5_SHIFT_REGISTER/STRUCTURAL_MODELING/1_SISO/D_FF.v


module d_ff(Q,D,clk,reset);

    input D,clk,reset;
    output reg Q;

    always @(posedge clk ) begin
        if(reset)
            Q<=0;
        else
            Q<=D;
    end

endmodule

5_SHIFT_REGISTER/STRUCTURAL_MODELING/3_PISO/PISO.v

`include "D_FF.v"

module piso(serial_out,parallel_in,clk,load,reset);

    input clk,load,reset;
    input [3:0] parallel_in;
    output serial_out;

    wire w1,w2,w3;
    wire d0,d1,d2,d3;

    assign d0=load?parallel_in[3]:1'b0;
    assign d1=load?parallel_in[2]:w1;
    assign d2=load?parallel_in[1]:w2;
    assign d3=load?parallel_in[0]:w3;

    d_ff x0(w1,d0,clk,reset);
    d_ff x1(w2,d1,clk,reset);
    d_ff x2(w3,d2,clk,reset);
    d_ff x3(serial_out,d3,clk,reset);

endmodule

5_SHIFT_REGISTER/STRUCTURAL_MODELING/3_PISO/PISO_TB.v

`include "PISO.v"

module piso_tb;

    reg [3:0] parallel_in;
    reg clk, load,reset;
    wire serial_out;

    piso dut(serial_out,parallel_in,clk,load,reset);

    always #5 clk = ~clk;

    initial begin
        $dumpfile("PISO.vcd");
        $dumpvars(0,piso_tb);
    end

    always @(posedge clk) begin
        $strobe($time,"  |   %b   |      %d     |     %d     ",reset,parallel_in,serial_out);
    end

    initial begin
        $display("                ---------------------------------------");
        $display("                 Time | Reset | Parallel_in | Serial_out ");
        $display("                ---------------------------------------");

        clk=0;
        load=0;
        reset=1;#7
        reset=0;

        parallel_in=4'b0000;#10
        load=1;
        parallel_in=4'b1101;#10
        load=0;
        #40
        $finish;

    end

endmodule

5_SHIFT_REGISTER/STRUCTURAL_MODELING/3_PISO/PISO.vcd
$date
	Mon Jun 15 16:39:14 2026
$end
$version
	Icarus Verilog
$end
$timescale
	1s
$end
$scope module piso_tb $end
$var wire 1 ! serial_out $end
$var reg 1 " clk $end
$var reg 1 # load $end
$var reg 4 $ parallel_in [3:0] $end
$var reg 1 % reset $end
$scope module dut $end
$var wire 1 & clk $end
$var wire 1 ' d0 $end
$var wire 1 ( d1 $end
$var wire 1 ) d2 $end
$var wire 1 * d3 $end
$var wire 1 + load $end
$var wire 4 , parallel_in [3:0] $end
$var wire 1 - reset $end
$var wire 1 ! serial_out $end
$var wire 1 . w1 $end
$var wire 1 / w2 $end
$var wire 1 0 w3 $end
$scope module x0 $end
$var wire 1 ' D $end
$var wire 1 & clk $end
$var wire 1 - reset $end
$var reg 1 1 Q $end
$upscope $end
$scope module x1 $end
$var wire 1 ( D $end
$var wire 1 & clk $end
$var wire 1 - reset $end
$var reg 1 2 Q $end
$upscope $end
$scope module x2 $end
$var wire 1 ) D $end
$var wire 1 & clk $end
$var wire 1 - reset $end
$var reg 1 3 Q $end
$upscope $end
$scope module x3 $end
$var wire 1 * D $end
$var wire 1 & clk $end
$var wire 1 - reset $end
$var reg 1 4 Q $end
$upscope $end
$upscope $end
$upscope $end
$enddefinitions $end
#0
$dumpvars
x4
x3
x2
x1
x0
x/
x.
1-
bx ,
0+
x*
x)
x(
0'
0&
1%
bx $
0#
0"
x!
$end
#5
0(
0)
0*
01
0.
02
0/
03
00
04
0!
1"
1&
#7
b0 $
b0 ,
0%
0-
#10
0"
0&
#15
1"
1&
#17
1'
1(
1*
b1101 $
b1101 ,
1#
1+
#20
0"
0&
#25
11
1.
12
1/
14
1!
1"
1&
#27
0'
1)
0*
0#
0+
#30
0"
0&
#35
1*
0(
04
0!
13
10
01
0.
1"
1&
#40
0"
0&
#45
0)
02
0/
14
1!
1"
1&
#50
0"
0&
#55
0*
03
00
1"
1&
#60
0"
0&
#65
04
0!
1"
1&
