2_COMBINATIONAL_CIRCUITS/Structural_Modeling/7_DECODER/DECODER_3X8/Decoder_2X4.v
module Decoder_2X4(I,A,B,En);

    input A, B, En;
    output reg [0:3] I;

    always @(*) begin
        if(En==1) I=4'b0000;
        else begin
            case ({A,B})
                0:I=4'b1000; 
                1:I=4'b0100; 
                2:I=4'b0010; 
                3:I=4'b0001;
            endcase
        end
    end

endmodule

2_COMBINATIONAL_CIRCUITS/Structural_Modeling/7_DECODER/DECODER_3X8/Decoder_3X8.v
`include "Decoder_2X4.v"

module Decoder_3X8(I, A, B, C);

    input A, B, C;
    output [0:7] I;
    wire C_n;

    not n(C_n,C);

    Decoder_2X4 D1(I[0:3],A,B,C);
    Decoder_2X4 D2(I[4:7],A,B,C_n);

endmodule

2_COMBINATIONAL_CIRCUITS/Structural_Modeling/7_DECODER/DECODER_3X8/Decoder_3X8_Tb.v
`include "Decoder_3X8.v"

module Decoder_3X8_Tb;

    reg A, B, C;
    wire [0:7] I;

    Decoder_3X8 dut(I,A,B,C);

    initial begin
        $dumpfile("Decoder_3X8.vcd");
        $dumpvars(0,Decoder_3X8_Tb);
    end

    initial begin
        
        $display("---------------------------");
        $display(" C | A | B ||  I[0:7]");
        $display("---------------------------");

        $monitor(" %b | %b | %b || %b ",C,A,B,I);
        C=0;A=0;B=0;
        #10 A=0;B=1;
        #10 A=1;B=0;
        #10 A=1;B=1;
        #10 C=1;A=0;B=0;
        #10 A=0;B=1;
        #10 A=1;B=0;
        #10 A=1;B=1;
        #10 $finish;
    end

endmodule

2_COMBINATIONAL_CIRCUITS/Structural_Modeling/7_DECODER/DECODER_3X8/Decoder_3X8.vcd
$date
	Mon Apr 13 19:33:50 2026
$end
$version
	Icarus Verilog
$end
$timescale
	1s
$end
$scope module Decoder_3X8_Tb $end
$var wire 8 ! I [0:7] $end
$var reg 1 " A $end
$var reg 1 # B $end
$var reg 1 $ C $end
$scope module dut $end
$var wire 1 % A $end
$var wire 1 & B $end
$var wire 1 ' C $end
$var wire 1 ( C_n $end
$var wire 8 ) I [0:7] $end
$scope module D1 $end
$var wire 1 % A $end
$var wire 1 & B $end
$var wire 1 ' En $end
$var reg 4 * I [0:3] $end
$upscope $end
$scope module D2 $end
$var wire 1 % A $end
$var wire 1 & B $end
$var wire 1 ( En $end
$var reg 4 + I [0:3] $end
$upscope $end
$upscope $end
$upscope $end
$enddefinitions $end
#0
$dumpvars
b0 +
b1000 *
b10000000 )
1(
0'
0&
0%
0$
0#
0"
b10000000 !
$end
#10
b100 *
b1000000 !
b1000000 )
1#
1&
#20
b10 *
b100000 !
b100000 )
0#
0&
1"
1%
#30
b1 *
b10000 !
b10000 )
1#
1&
#40
b1000 +
0(
b0 *
b1000 !
b1000 )
0#
0&
0"
0%
1$
1'
#50
b100 +
b100 !
b100 )
1#
1&
#60
b10 +
b10 !
b10 )
0#
0&
1"
1%
#70
b1 +
b1 !
b1 )
1#
1&
