2_COMBINATIONAL_CIRCUITS/Behavioral_Modeling/10_CODE_CONVERTER/3_BIT_BINARY_TO_GRAY_CODE/B_To_G.v
module B_To_G (G,B);
    input  [2:0] B;
    output reg [2:0] G;

    always @(*)
    begin
        G[2] = B[2];
        G[1] = B[2] ^ B[1];
        G[0] = B[1] ^ B[0];
    end

endmodule

2_COMBINATIONAL_CIRCUITS/Behavioral_Modeling/10_CODE_CONVERTER/3_BIT_BINARY_TO_GRAY_CODE/B-To_G_Tb.v
`include "B_To_G.v"

module B_To_G_Tb;

    reg [2:0] I; 
    wire [2:0] O;

    B_To_G dut(O,I);

    initial begin
        $dumpfile("B_To_G.vcd");
        $dumpvars(0,B_To_G_Tb);
    end

    initial begin
        
        $display("------------------------------");
        $display(" I2 | I1 | I0 || Y2 | Y1 | Y0");
        $display("------------------------------");

        $monitor("  %b |  %b |  %b ||  %b |  %b | %b ",I[2],I[1],I[0],O[2],O[1],O[0]);

        I=3'b000;#10
        I=3'b001;#10
        I=3'b010;#10
        I=3'b011;#10
        I=3'b100;#10
        I=3'b101;#10
        I=3'b110;#10
        I=3'b111;#10
        $finish;

    end

endmodule

2_COMBINATIONAL_CIRCUITS/Behavioral_Modeling/10_CODE_CONVERTER/3_BIT_BINARY_TO_GRAY_CODE/B_To_G.vcd
$date
	Wed Apr 15 18:30:57 2026
$end
$version
	Icarus Verilog
$end
$timescale
	1s
$end
$scope module B_To_G_Tb $end
$var wire 3 ! O [2:0] $end
$var reg 3 " I [2:0] $end
$scope module dut $end
$var wire 3 # B [2:0] $end
$var reg 3 $ G [2:0] $end
$upscope $end
$upscope $end
$enddefinitions $end
#0
$dumpvars
b0 $
b0 #
b0 "
b0 !
$end
#10
b1 !
b1 $
b1 "
b1 #
#20
b11 !
b11 $
b10 "
b10 #
#30
b10 !
b10 $
b11 "
b11 #
#40
b110 $
b110 !
b100 "
b100 #
#50
b111 !
b111 $
b101 "
b101 #
#60
b101 !
b101 $
b110 "
b110 #
#70
b100 !
b100 $
b111 "
b111 #
