6_COUNTER/STRUCTURAL_MODELING/JOHNSON_COUNTER/d_ff.v

module d_ff(q,q_bar,d,clk,reset);

    input d,clk,reset;
    output reg q;
    output q_bar;

    always @(posedge clk or posedge reset) begin
        if(reset)
            q<=0;
        else
            q<=d;
    end

    assign q_bar=~q;
 
endmodule

6_COUNTER/STRUCTURAL_MODELING/JOHNSON_COUNTER/JOHNSON_COUNTER.v


`include "d_ff.v"

module johnson_counter(Q,clk,reset);

    input clk,reset;
    output Q;

    wire A,B,C,D;

    d_ff d0(.q(A),.q_bar(),.d(D),.clk(clk),.reset(reset));
    d_ff d1(.q(B),.q_bar(),.d(A),.clk(clk),.reset(reset));
    d_ff d2(.q(C),.q_bar(),.d(B),.clk(clk),.reset(reset));
    d_ff d3(.q(Q),.q_bar(D),.d(C),.clk(clk),.reset(reset));

endmodule

6_COUNTER/STRUCTURAL_MODELING/JOHNSON_COUNTER/JOHNSON_COUNTER_TB.v


`include "JOHNSON_COUNTER.v"

module johnson_counter_tb;

    reg clk,reset;
    wire q;

    always #5 clk=~clk;

    johnson_counter dut(q,clk,reset);

    initial begin
        $dumpfile("JOHNSON_COUNTER.vcd");
        $dumpvars(0,johnson_counter_tb);
    end

    always @(posedge clk) begin
        $strobe($time,"   | %b ",q);
    end

    initial begin

        $display("                  ----------");
        $display("                  Time | Q ");
        $display("                  ----------");

        reset=1;
        clk=0;
        #10;
        reset=0;
        #200
        $finish;
    end

endmodule

6_COUNTER/STRUCTURAL_MODELING/JOHNSON_COUNTER/JOHNSON_COUNTER.vcd
$date
	Mon Jun 15 18:14:06 2026
$end
$version
	Icarus Verilog
$end
$timescale
	1s
$end
$scope module johnson_counter_tb $end
$var wire 1 ! q $end
$var reg 1 " clk $end
$var reg 1 # reset $end
$scope module dut $end
$var wire 1 $ A $end
$var wire 1 % B $end
$var wire 1 & C $end
$var wire 1 ' D $end
$var wire 1 ! Q $end
$var wire 1 ( clk $end
$var wire 1 ) reset $end
$scope module d0 $end
$var wire 1 ( clk $end
$var wire 1 ' d $end
$var wire 1 * q_bar $end
$var wire 1 ) reset $end
$var reg 1 + q $end
$upscope $end
$scope module d1 $end
$var wire 1 ( clk $end
$var wire 1 $ d $end
$var wire 1 , q_bar $end
$var wire 1 ) reset $end
$var reg 1 - q $end
$upscope $end
$scope module d2 $end
$var wire 1 ( clk $end
$var wire 1 % d $end
$var wire 1 . q_bar $end
$var wire 1 ) reset $end
$var reg 1 / q $end
$upscope $end
$scope module d3 $end
$var wire 1 ( clk $end
$var wire 1 & d $end
$var wire 1 ' q_bar $end
$var wire 1 ) reset $end
$var reg 1 0 q $end
$upscope $end
$upscope $end
$upscope $end
$enddefinitions $end
#0
$dumpvars
00
0/
1.
0-
1,
0+
1*
1)
0(
1'
0&
0%
0$
1#
0"
0!
$end
#5
1"
1(
#10
0"
0(
0#
0)
#15
0*
1+
1$
1"
1(
#20
0"
0(
#25
0,
1-
1%
1"
1(
#30
0"
0(
#35
0.
1/
1&
1"
1(
#40
0"
0(
#45
0'
10
1!
1"
1(
#50
0"
0(
#55
1*
0+
0$
1"
1(
#60
0"
0(
#65
1,
0-
0%
1"
1(
#70
0"
0(
#75
1.
0/
0&
1"
1(
#80
0"
0(
#85
1'
00
0!
1"
1(
#90
0"
0(
#95
0*
1+
1$
1"
1(
#100
0"
0(
#105
0,
1-
1%
1"
1(
#110
0"
0(
#115
0.
1/
1&
1"
1(
#120
0"
0(
#125
0'
10
1!
1"
1(
#130
0"
0(
#135
1*
0+
0$
1"
1(
#140
0"
0(
#145
1,
0-
0%
1"
1(
#150
0"
0(
#155
1.
0/
0&
1"
1(
#160
0"
0(
#165
1'
00
0!
1"
1(
#170
0"
0(
#175
0*
1+
1$
1"
1(
#180
0"
0(
#185
0,
1-
1%
1"
1(
#190
0"
0(
#195
0.
1/
1&
1"
1(
#200
0"
0(
#205
0'
10
1!
1"
1(
