4_REGISTERS/4_BIT_REGISTER_STRUCTURAL/D_FF.v
//Behaviour modelling of D Flip Flop 

module D_FF(D,Q,clk,reset);

    input Q,clk,reset;
    output reg D;

    always @(posedge clk or posedge reset) begin
        if(reset)
            D<=1'b0;
        else
            D<=Q;
    end

endmodule

4_REGISTERS/4_BIT_REGISTER_STRUCTURAL/4_Bit_Reg.v
//4 Bit Register(Structural Modeling) using Behavioural Modelled Asynchronous D Flip Flop 

`include "D_FF.v"

module fourbit_reg(D,Q,clk,reset);

    input [3:0] Q;
    input clk,reset;
    output [3:0] D;

    D_FF ff0(D[0],Q[0],clk,reset);
    D_FF ff1(D[1],Q[1],clk,reset);
    D_FF ff2(D[2],Q[2],clk,reset);
    D_FF ff3(D[3],Q[3],clk,reset);

endmodule

4_REGISTERS/4_BIT_REGISTER_STRUCTURAL/4_Bit_Reg_Tb.v


`include "4_Bit_Reg.v"

module fourbit_reg_tb;

    reg [3:0] Q ;
    reg clk, reset;
    wire [3:0] D ;

    fourbit_reg dut(D,Q,clk,reset);

    always #5 clk = ~clk;

    initial begin
        $dumpfile("4_Bit_Reg.vcd");
        $dumpvars(0,fourbit_reg_tb);
    end

    always @(posedge clk) begin
        $strobe($time,"  |   %b   | %d | %d ",reset,Q,D);
    end

    initial begin
        $display("                -----------------------");
        $display("                 Time | Reset | Q  | D ");
        $display("                -----------------------");
        
        clk=0;
        #7
        Q=4'b0010;#10
        Q=4'b0101;#10
        Q=4'b1111;#10
        Q=4'b1011;#10
        $finish;
    end

    initial begin
        reset=1;#7
        reset=0;
    end

endmodule

4_REGISTERS/4_BIT_REGISTER_STRUCTURAL/4_Bit_Reg.vcd
$date
	Mon Jun 15 13:28:43 2026
$end
$version
	Icarus Verilog
$end
$timescale
	1s
$end
$scope module fourbit_reg_tb $end
$var wire 4 ! D [3:0] $end
$var reg 4 " Q [3:0] $end
$var reg 1 # clk $end
$var reg 1 $ reset $end
$scope module dut $end
$var wire 4 % D [3:0] $end
$var wire 4 & Q [3:0] $end
$var wire 1 ' clk $end
$var wire 1 ( reset $end
$scope module ff0 $end
$var wire 1 ) Q $end
$var wire 1 ' clk $end
$var wire 1 ( reset $end
$var reg 1 * D $end
$upscope $end
$scope module ff1 $end
$var wire 1 + Q $end
$var wire 1 ' clk $end
$var wire 1 ( reset $end
$var reg 1 , D $end
$upscope $end
$scope module ff2 $end
$var wire 1 - Q $end
$var wire 1 ' clk $end
$var wire 1 ( reset $end
$var reg 1 . D $end
$upscope $end
$scope module ff3 $end
$var wire 1 / Q $end
$var wire 1 ' clk $end
$var wire 1 ( reset $end
$var reg 1 0 D $end
$upscope $end
$upscope $end
$upscope $end
$enddefinitions $end
#0
$dumpvars
00
x/
0.
x-
0,
x+
0*
x)
1(
0'
bx &
b0 %
1$
0#
bx "
b0 !
$end
#5
1#
1'
#7
0)
1+
0-
0/
0$
0(
b10 "
b10 &
#10
0#
0'
#15
1,
b10 !
b10 %
1#
1'
#17
1)
0+
1-
b101 "
b101 &
#20
0#
0'
#25
1.
0,
1*
b101 !
b101 %
1#
1'
#27
1+
1/
b1111 "
b1111 &
#30
0#
0'
#35
1,
10
b1111 !
b1111 %
1#
1'
#37
0-
b1011 "
b1011 &
#40
0#
0'
#45
0.
b1011 !
b1011 %
1#
1'
