2_COMBINATIONAL_CIRCUITS/Behavioral_Modeling/10_CODE_CONVERTER/BCD_TO_7SEGMENT/Bcd_To_7Segment.v
//BCD To 7 Segment code


module Bcd_To_7Segment(A, B, C, D, a, b, c, d, e, f, g);

    input A, B, C, D;
    output reg a, b, c, d, e, f, g;

    always @(*) begin
        case({A,B,C,D})

        4'b0000: {a,b,c,d,e,f,g} = 7'b1111110; 
        4'b0001: {a,b,c,d,e,f,g} = 7'b0110000; 
        4'b0010: {a,b,c,d,e,f,g} = 7'b1101101; 
        4'b0011: {a,b,c,d,e,f,g} = 7'b1111001; 
        4'b0100: {a,b,c,d,e,f,g} = 7'b0110011; 
        4'b0101: {a,b,c,d,e,f,g} = 7'b1011011; 
        4'b0110: {a,b,c,d,e,f,g} = 7'b1011111; 
        4'b0111: {a,b,c,d,e,f,g} = 7'b1110000; 
        4'b1000: {a,b,c,d,e,f,g} = 7'b1111111; 
        4'b1001: {a,b,c,d,e,f,g} = 7'b1111011; 

        default: {a,b,c,d,e,f,g} = 7'bx;

    endcase
    end

endmodule

2_COMBINATIONAL_CIRCUITS/Behavioral_Modeling/10_CODE_CONVERTER/BCD_TO_7SEGMENT/Bcd_To_7Segment_Tb.v
`include "Bcd_To_7Segment.v"

module Bcd_To_7Segment_Tb;

    reg A,B,C,D;
    wire a,b,c,d,e,f,g;

    Bcd_To_7Segment dut(A,B,C,D,a,b,c,d,e,f,g);

    initial begin
        $dumpfile("Bcd_To_7Segment.vcd");
        $dumpvars(0,Bcd_To_7Segment_Tb);
    end

    initial begin
        
        $display("---------------------------------------------");
        $display(" A | B | C | D || a | b | c | d | e | f | g ");
        $display("---------------------------------------------");

        $monitor(" %b | %b | %b | %b || %b | %b | %b | %b | %b | %b | %b  ",A,B,C,D,a,b,c,d,e,f,g);

        {A,B,C,D}=4'b0000;#10
        {A,B,C,D}=4'b0001;#10
        {A,B,C,D}=4'b0010;#10
        {A,B,C,D}=4'b0011;#10
        {A,B,C,D}=4'b0100;#10
        {A,B,C,D}=4'b0101;#10
        {A,B,C,D}=4'b0110;#10
        {A,B,C,D}=4'b0111;#10
        {A,B,C,D}=4'b1000;#10
        {A,B,C,D}=4'b1001;#10
        $finish;
        $display("---------------------------------------------");

    end

endmodule

2_COMBINATIONAL_CIRCUITS/Behavioral_Modeling/10_CODE_CONVERTER/BCD_TO_7SEGMENT/Bcd_To_7Segment.vcd
$date
	Wed Apr 15 18:41:50 2026
$end
$version
	Icarus Verilog
$end
$timescale
	1s
$end
$scope module Bcd_To_7Segment_Tb $end
$var wire 1 ! a $end
$var wire 1 " b $end
$var wire 1 # c $end
$var wire 1 $ d $end
$var wire 1 % e $end
$var wire 1 & f $end
$var wire 1 ' g $end
$var reg 1 ( A $end
$var reg 1 ) B $end
$var reg 1 * C $end
$var reg 1 + D $end
$scope module dut $end
$var wire 1 , A $end
$var wire 1 - B $end
$var wire 1 . C $end
$var wire 1 / D $end
$var reg 1 0 a $end
$var reg 1 1 b $end
$var reg 1 2 c $end
$var reg 1 3 d $end
$var reg 1 4 e $end
$var reg 1 5 f $end
$var reg 1 6 g $end
$upscope $end
$upscope $end
$enddefinitions $end
#0
$dumpvars
06
15
14
13
12
11
10
0/
0.
0-
0,
0+
0*
0)
0(
0'
1&
1%
1$
1#
1"
1!
$end
#10
00
0!
03
0$
04
0%
05
0&
1+
1/
#20
10
1!
02
0#
13
1$
14
1%
16
1'
1*
1.
0+
0/
#30
12
1#
04
0%
1+
1/
#40
00
0!
03
0$
15
1&
1)
1-
0*
0.
0+
0/
#50
10
1!
01
0"
13
1$
1+
1/
#60
14
1%
1*
1.
0+
0/
#70
11
1"
03
0$
04
0%
05
0&
06
0'
1+
1/
#80
13
1$
14
1%
15
1&
16
1'
1(
1,
0)
0-
0*
0.
0+
0/
#90
04
0%
1+
1/
