6_COUNTER/STRUCTURAL_MODELING/SYNC_4_BIT_COUNTER/T_FF.v

module  t_ff(D,T,clk,reset);
    
    input clk,reset,T;
    output reg D;

    always @(posedge clk or posedge reset) begin
        if(reset)
            D<=0;
        else if(T)
            D<=~D;
        else
            D<=D;
    end

endmodule

6_COUNTER/STRUCTURAL_MODELING/SYNC_4_BIT_COUNTER/4_BIT_COUNTER.v

`include "T_FF.v"

module four_bit_counter(Q,clk,reset);

    input clk,reset;
    output [3:0] Q;

    wire w1, w2;

    and a2(w1,Q[0],Q[1]);
    and a3(w2,Q[0],Q[1],Q[2]);

    t_ff t1(Q[0],1'b1,clk,reset);
    t_ff t2(Q[1],Q[0],clk,reset);
    t_ff t3(Q[2],w1,clk,reset);
    t_ff t4(Q[3],w2,clk,reset);


endmodule

6_COUNTER/STRUCTURAL_MODELING/SYNC_4_BIT_COUNTER/4_BIT_COUNTER_TB.v



`include "4_BIT_COUNTER.v"

module four_bit_counter_tb;

    reg clk,reset;
    wire [3:0] Q;

    always #5 clk=~clk;

    four_bit_counter dut(Q,clk,reset);

    initial begin
        $dumpfile("4_BIT_COUNTER.vcd");
        $dumpvars(0,four_bit_counter_tb);
    end

    always @(posedge clk) begin
        $strobe($time,"   | %b ",Q);
    end

    initial begin

        $display("                  ----------");
        $display("                  Time | Q ");
        $display("                  ----------");

        clk=0;
        reset=1;#7
        reset=0;
        #200;
        $finish;
    end

endmodule

6_COUNTER/STRUCTURAL_MODELING/SYNC_4_BIT_COUNTER/4_BIT_COUNTER.vcd
$date
	Mon Jun 15 18:15:05 2026
$end
$version
	Icarus Verilog
$end
$timescale
	1s
$end
$scope module four_bit_counter_tb $end
$var wire 4 ! Q [3:0] $end
$var reg 1 " clk $end
$var reg 1 # reset $end
$scope module dut $end
$var wire 4 $ Q [3:0] $end
$var wire 1 % clk $end
$var wire 1 & reset $end
$var wire 1 ' w1 $end
$var wire 1 ( w2 $end
$scope module t1 $end
$var wire 1 ) T $end
$var wire 1 % clk $end
$var wire 1 & reset $end
$var reg 1 * D $end
$upscope $end
$scope module t2 $end
$var wire 1 + T $end
$var wire 1 % clk $end
$var wire 1 & reset $end
$var reg 1 , D $end
$upscope $end
$scope module t3 $end
$var wire 1 ' T $end
$var wire 1 % clk $end
$var wire 1 & reset $end
$var reg 1 - D $end
$upscope $end
$scope module t4 $end
$var wire 1 ( T $end
$var wire 1 % clk $end
$var wire 1 & reset $end
$var reg 1 . D $end
$upscope $end
$upscope $end
$upscope $end
$enddefinitions $end
#0
$dumpvars
0.
0-
0,
0+
0*
1)
0(
0'
1&
0%
b0 $
1#
0"
b0 !
$end
#5
1"
1%
#7
0#
0&
#10
0"
0%
#15
1+
1*
b1 !
b1 $
1"
1%
#20
0"
0%
#25
0+
1,
0*
b10 !
b10 $
1"
1%
#30
0"
0%
#35
1'
1+
1*
b11 !
b11 $
1"
1%
#40
0"
0%
#45
0'
0+
1-
0,
0*
b100 !
b100 $
1"
1%
#50
0"
0%
#55
1+
1*
b101 !
b101 $
1"
1%
#60
0"
0%
#65
0+
1,
0*
b110 !
b110 $
1"
1%
#70
0"
0%
#75
1'
1(
1+
1*
b111 !
b111 $
1"
1%
#80
0"
0%
#85
0'
0(
0+
1.
0-
0,
0*
b1000 !
b1000 $
1"
1%
#90
0"
0%
#95
1+
1*
b1001 !
b1001 $
1"
1%
#100
0"
0%
#105
0+
1,
0*
b1010 !
b1010 $
1"
1%
#110
0"
0%
#115
1'
1+
1*
b1011 !
b1011 $
1"
1%
#120
0"
0%
#125
0'
0+
1-
0,
0*
b1100 !
b1100 $
1"
1%
#130
0"
0%
#135
1+
1*
b1101 !
b1101 $
1"
1%
#140
0"
0%
#145
0+
1,
0*
b1110 !
b1110 $
1"
1%
#150
0"
0%
#155
1'
1(
1+
1*
b1111 !
b1111 $
1"
1%
#160
0"
0%
#165
0'
0(
0+
0.
0-
0,
0*
b0 !
b0 $
1"
1%
#170
0"
0%
#175
1+
1*
b1 !
b1 $
1"
1%
#180
0"
0%
#185
0+
1,
0*
b10 !
b10 $
1"
1%
#190
0"
0%
#195
1'
1+
1*
b11 !
b11 $
1"
1%
#200
0"
0%
#205
0'
0+
1-
0,
0*
b100 !
b100 $
1"
1%
