5_SHIFT_REGISTER/BEHAVIOR_MODELING/2_SIPO/SIPO.v

module sipo(parallel_out, serial_in, clk, reset);

    input serial_in, clk, reset;
    output reg [3:0] parallel_out;



    always @(posedge clk or posedge reset) begin
        if(reset)
            parallel_out<={4{1'b0}};
        else
            parallel_out<={serial_in,parallel_out[3:1]};
    end

endmodule

5_SHIFT_REGISTER/BEHAVIOR_MODELING/2_SIPO/SIPO_TB.v

`include "SIPO.v"

module sipo_tb;

    reg serial_in, clk, reset;
    wire [3:0] parallel_out;

    sipo dut(parallel_out,serial_in,clk,reset);

    always #5 clk=~clk;

    initial begin
        $dumpfile("SIPO.vcd");
        $dumpvars(0,sipo_tb);
    end
    
    always @(posedge clk) begin
        $strobe($time,"  |   %b   |     %d     |     %d     ",reset,serial_in,parallel_out);
    end
    
    initial begin

        $display("                -----------------------------------------");
        $display("                 Time | Reset | Serial_in | parallel_out ");
        $display("                -----------------------------------------");

        // $monitor($time," serial_in=%b, parallel_out=%b",serial_in, parallel_out);

        clk=0;
        reset=1;#7
        reset=0;
        serial_in=1;#10
        serial_in=0;#10
        serial_in=0;#10
        serial_in=1;#10
        $finish;
    end

endmodule

5_SHIFT_REGISTER/BEHAVIOR_MODELING/2_SIPO/SIPO.vcd
$date
	Mon Jun 15 13:43:29 2026
$end
$version
	Icarus Verilog
$end
$timescale
	1s
$end
$scope module sipo_tb $end
$var wire 4 ! parallel_out [3:0] $end
$var reg 1 " clk $end
$var reg 1 # reset $end
$var reg 1 $ serial_in $end
$scope module dut $end
$var wire 1 % clk $end
$var wire 1 & reset $end
$var wire 1 ' serial_in $end
$var reg 4 ( parallel_out [3:0] $end
$upscope $end
$upscope $end
$enddefinitions $end
#0
$dumpvars
b0 (
x'
1&
0%
x$
1#
0"
b0 !
$end
#5
1"
1%
#7
1$
1'
0#
0&
#10
0"
0%
#15
b1000 (
b1000 !
1"
1%
#17
0$
0'
#20
0"
0%
#25
b100 (
b100 !
1"
1%
#30
0"
0%
#35
b10 (
b10 !
1"
1%
#37
1$
1'
#40
0"
0%
#45
b1001 (
b1001 !
1"
1%
