2_COMBINATIONAL_CIRCUITS/Structural_Modeling/3_HALF_SUBTRACTOR/Half_Subtractor.v
module Half_Subtractor(Borrow, Diff, A, B);

    input A, B;
    output Diff, Borrow;
    wire w0;

    xor h0(Diff, A, B);
    not h1(w0,A);
    and h2(Borrow, w0, B);
    
endmodule

2_COMBINATIONAL_CIRCUITS/Structural_Modeling/3_HALF_SUBTRACTOR/Half_Subtractor_Tb.v

`timescale 1ns/1ps
`include "Half_Subtractor.v"

module Half_Subtractor_Tb;
    
    reg A, B;
    wire Diff, Borrow;

    integer i,j;
    reg [3:0] val;


    Half_Subtractor DUT (Borrow, Diff, A, B);

    initial begin
        //$monitor($time," A = %b , B = %b , Diff = %b , Borrow = %b", A, B, Diff, Borrow);
        $dumpfile("Half_Subtractor.vcd");
        $dumpvars(0,Half_Subtractor_Tb);
    end

    initial begin
    val[0]=1'b0;
    val[1]=1'b1;
    val[2]=1'bx;
    val[3]=1'bz;

    $display("\t\t\t\t ","-----------------------------");
    $display("\t\t\t\t  ","time| A | B |Diff | Borrow");
    $display("\t\t\t\t ","-----------------------------");

    for(i=0;i<2;i=i+1)begin
      A=val[i];
      for(j=0;j<2;j=j+1)begin
        B=val[j];
        #5 $write($time,"  | %b | %b |  %b  |  %b\n",A,B,Diff,Borrow);
      end
    end

    $display("\t\t\t\t ","-------------------------");

    for(i=2;i<4;i=i+1)begin
      A=val[i];
      for(j=0;j<4;j=j+1)begin
        B=val[j];
        #5 $write($time,"  | %b | %b |  %b  |  %b\n",A,B,Diff,Borrow);
      end
    end
    
    #5 $finish;

  end

endmodule

2_COMBINATIONAL_CIRCUITS/Structural_Modeling/3_HALF_SUBTRACTOR/Half_Subtractor.vcd
$date
	Thu Apr 09 23:05:00 2026
$end
$version
	Icarus Verilog
$end
$timescale
	1ps
$end
$scope module Half_Subtractor_Tb $end
$var wire 1 ! Borrow $end
$var wire 1 " Diff $end
$var reg 1 # A $end
$var reg 1 $ B $end
$var integer 32 % i [31:0] $end
$var integer 32 & j [31:0] $end
$var reg 4 ' val [3:0] $end
$scope module DUT $end
$var wire 1 ( A $end
$var wire 1 ) B $end
$var wire 1 ! Borrow $end
$var wire 1 " Diff $end
$var wire 1 * w0 $end
$upscope $end
$upscope $end
$enddefinitions $end
#0
$dumpvars
1*
0)
0(
bzx10 '
b0 &
b0 %
0$
0#
0"
0!
$end
#5000
1"
1!
1$
1)
b1 &
#10000
0!
0*
0$
0)
1#
1(
b1 %
b0 &
#15000
0"
1$
1)
b1 &
#20000
x"
x*
0$
0)
x#
x(
b10 %
b0 &
#25000
x!
1$
1)
b1 &
#30000
x$
x)
b10 &
#35000
z$
z)
b11 &
#40000
0!
0$
0)
z#
z(
b11 %
b0 &
#45000
x!
1$
1)
b1 &
#50000
x$
x)
b10 &
#55000
z$
z)
b11 &
#60000
b100 %
b100 &
